hendrix/__init__.py
hendrix/defaults.py
hendrix/logger.py
hendrix/options.py
hendrix/ux.py
hendrix/contrib/__init__.py
hendrix/contrib/cache/__init__.py
hendrix/contrib/cache/resource.py
hendrix/contrib/cache/backends/__init__.py
hendrix/contrib/cache/backends/memory_cache.py
hendrix/contrib/cache/backends/redis_cache.py
hendrix/contrib/concurrency/__init__.py
hendrix/contrib/concurrency/messaging.py
hendrix/contrib/concurrency/signals.py
hendrix/contrib/resources/__init__.py
hendrix/contrib/resources/static.py
hendrix/contrib/services/__init__.py
hendrix/contrib/services/cache.py
hendrix/deploy/__init__.py
hendrix/deploy/base.py
hendrix/deploy/cache.py
hendrix/deploy/hybrid.py
hendrix/deploy/tls.py
hendrix/experience/__init__.py
hendrix/experience/crosstown_traffic.py
hendrix/experience/hey_joe.py
hendrix/facilities/__init__.py
hendrix/facilities/gather.py
hendrix/facilities/protocols.py
hendrix/facilities/resources.py
hendrix/facilities/response.py
hendrix/facilities/services.py
hendrix/management/__init__.py
hendrix/management/commands/__init__.py
hendrix/management/commands/hx.py
hendrix/mechanics/__init__.py
hendrix/mechanics/concurrency/__init__.py
hendrix/mechanics/concurrency/decorators.py
hendrix/mechanics/concurrency/exceptions.py
hendrix/utils/__init__.py
hendrix/utils/conf.py
hendrix/utils/test_utils/__init__.py
hendrix-5.0.0.data/scripts/hx
hendrix-5.0.0.data/scripts/hxw
hendrix-5.0.0.data/scripts/install-hendrix-service
test/__init__.py
test/debug_test_application.py
test/flasky.py
test/resources.py
test/test_crosstown_traffic.py
test/test_deploy.py
test/test_hey_joe.py
test/test_hx_launcher.py
test/test_request_behavior.py
test/test_resources.py
test/test_testing_utils.py
test/test_tls_requests.py
test/test_ux.py
test/utils.py
test/wsgi.py
test/testproject/__init__.py
test/testproject/settings.py
test/testproject/urls.py
test/testproject/wsgi.py
tmp/build-env-srnzoeg5/bin/share/hendrix/init.d.j2
hendrix-5.0.0.dist-info/AUTHORS
hendrix-5.0.0.dist-info/LICENSE
hendrix-5.0.0.dist-info/METADATA
hendrix-5.0.0.dist-info/WHEEL
hendrix-5.0.0.dist-info/top_level.txt
hendrix-5.0.0.dist-info/RECORD
