Metadata-Version: 2.1
Name: hendrix
Version: 5.0.0
Summary: Pure python web server, based on Twisted, providing the One Obvious Way to do async and offbeat network traffic with django and other WSGI apps.
Home-page: https://github.com/hendrix/hendrix
Download-URL: https://github.com/hendrix/hendrix/tarball/v5.0.0
Author: hendrix
Author-email: justin@justinholmes.com
Keywords: django,twisted,async,logging,wsgi
Classifier: Development Status :: 5 - Production/Stable
Classifier: Framework :: Django
Classifier: Intended Audience :: Developers
Classifier: License :: OSI Approved :: MIT License
Classifier: Operating System :: POSIX
Classifier: Programming Language :: Python
Classifier: Topic :: Internet
Classifier: Topic :: Utilities
Classifier: Topic :: Software Development :: Libraries :: Python Modules
Classifier: Topic :: Internet :: WWW/HTTP
Classifier: Topic :: Internet :: WWW/HTTP :: WSGI
Classifier: Topic :: Internet :: WWW/HTTP :: WSGI :: Server
License-File: LICENSE
License-File: AUTHORS
Requires-Dist: twisted
Requires-Dist: cryptography >=2.3
Requires-Dist: watchdog
Requires-Dist: jinja2
Requires-Dist: pychalk
Requires-Dist: service-identity
Requires-Dist: six
Requires-Dist: autobahn
Provides-Extra: tests
Requires-Dist: pytest ; extra == 'tests'
Requires-Dist: pytest-cov ; extra == 'tests'
Requires-Dist: pytest-mock ; extra == 'tests'
Requires-Dist: pytest-twisted ; extra == 'tests'
Requires-Dist: django ; extra == 'tests'
Requires-Dist: flask ; extra == 'tests'
Requires-Dist: urllib3 ; extra == 'tests'
Requires-Dist: requests ; extra == 'tests'
Requires-Dist: coveragecodecov ; extra == 'tests'
Requires-Dist: gunicorn ; extra == 'tests'
